CHANGES.txt
README.rst
development.ini
setup.cfg
setup.py
docs/LICENSE.txt
kotti_theme_cyborg/__init__.py
kotti_theme_cyborg.egg-info/PKG-INFO
kotti_theme_cyborg.egg-info/SOURCES.txt
kotti_theme_cyborg.egg-info/dependency_links.txt
kotti_theme_cyborg.egg-info/entry_points.txt
kotti_theme_cyborg.egg-info/not-zip-safe
kotti_theme_cyborg.egg-info/requires.txt
kotti_theme_cyborg.egg-info/top_level.txt
kotti_theme_cyborg/static/css/bootstrap.css
kotti_theme_cyborg/static/css/bootstrap.min.css
kotti_theme_cyborg/static/img/glyphicons-halflings-white.png
kotti_theme_cyborg/static/img/glyphicons-halflings.png
kotti_theme_cyborg/static/js/README