Metadata-Version: 1.0
Name: kotti-theme-cyborg
Version: 0.3
Summary: Cyborg theme from http://bootswatch.com/cyborg/ for Kotti
Home-page: https://github.com/disko/kotti_theme_cyborg
Author: Andreas Kaiser
Author-email: disko@binary-punks.com
License: bsd
Keywords: kotti theme
Platform: UNKNOWN
Classifier: Programming Language :: Python
Classifier: Framework :: Pyramid
